timesheet_common_timesheet_mfdenison_hopkinsep/__init__.py
timesheet_common_timesheet_mfdenison_hopkinsep/database.py
timesheet_common_timesheet_mfdenison_hopkinsep/models.py
timesheet_common_timesheet_mfdenison_hopkinsep/serializers.py
timesheet_common_timesheet_mfdenison_hopkinsep/utils/__init__.py
timesheet_common_timesheet_mfdenison_hopkinsep/utils/dashboard.py
timesheet_common_timesheet_mfdenison_hopkinsep/utils/timelog_update_manager.py
timesheet_common_timesheet_mfdenison_hopkinsep-0.0.3.dist-info/METADATA
timesheet_common_timesheet_mfdenison_hopkinsep-0.0.3.dist-info/WHEEL
timesheet_common_timesheet_mfdenison_hopkinsep-0.0.3.dist-info/top_level.txt
timesheet_common_timesheet_mfdenison_hopkinsep-0.0.3.dist-info/RECORD
